skrapa/__init__.py
skrapa/base.py
skrapa/exceptions.py
skrapa/linux/__init__.py
skrapa/linux/attributes.py
skrapa/linux/base.py
skrapa/linux/helpers.py
skrapa/windows/__init__.py
skrapa/windows/attributes.py
skrapa/windows/base.py
skrapa/windows/helpers.py
skrapa-1.0.dist-info/LICENSE
skrapa-1.0.dist-info/METADATA
skrapa-1.0.dist-info/WHEEL
skrapa-1.0.dist-info/top_level.txt
skrapa-1.0.dist-info/RECORD
