Metadata-Version: 2.1
Name: skrapa
Version: 1.0
Summary: Minimal Python memory scraper with memory attributes support
Author-email: Axel Boesenach <axel.boesenach@fox-it.com>, Erik Schamper <erik.schamper@fox-it.com>
License: Apache License 2.0
Project-URL: repository, https://github.com/fox-it/skrapa
Classifier: Development Status :: 5 - Production/Stable
Classifier: Environment :: Console
Classifier: Intended Audience :: Developers
Classifier: Intended Audience :: Information Technology
Classifier: License :: OSI Approved
Classifier: Operating System :: OS Independent
Classifier: Programming Language :: Python :: 3
Classifier: Topic :: Security
Classifier: Topic :: Utilities
Requires-Python: ~=3.7
License-File: LICENSE
Provides-Extra: yara
Requires-Dist: yara-python-wheel ==4.4.0 ; extra == 'yara'
